{
    "0.05": [
        {
            "U": 0.05,
            "ILP": true,
            "ILPDS": true,
            "gamma": "T2: ['4568,303269', '6540,454904'], T1: ['7700,237022', '10877,355533'], T0: ['469,191279', '610,286919']",
            "dgamma": "T0: ['469,191279', '610,286919'], T1: ['7700,237022', '10877,355533'], T2: ['4568,303269', '6540,454904']",
            "connections": [
                0,
                1,
                2
            ],
            "overlapping_modes": {
                "0": "T0: 469,191279, T1: 7700,237022, T2: 4568,303269, T2: 6540,454904",
                "1": "T0: 469,191279, T1: 7700,237022, T1: 10877,355533, T2: 4568,303269",
                "2": "T0: 469,191279, T0: 610,286919, T1: 7700,237022, T2: 4568,303269"
            }
        }
    ],
    "0.1": [
        {
            "U": 0.1,
            "ILP": true,
            "ILPDS": true,
            "gamma": "T2: ['2071,49373', '2368,74059'], T1: ['124,10916', '145,16373'], T0: ['906,21598', '1512,32396']",
            "dgamma": "T0: ['906,21598', '1512,32396'], T1: ['124,10916', '145,16373'], T2: ['2071,49373', '2368,74059']",
            "connections": [
                0,
                1,
                2
            ],
            "overlapping_modes": {
                "0": "T0: 906,21598, T1: 124,10916, T2: 2071,49373, T2: 2368,74059",
                "1": "T0: 906,21598, T1: 124,10916, T1: 145,16373, T2: 2071,49373",
                "2": "T0: 906,21598, T0: 1512,32396, T1: 124,10916, T2: 2071,49373"
            }
        }
    ],
    "0.15": [
        {
            "U": 0.15,
            "ILP": true,
            "ILPDS": true,
            "gamma": "T2: ['7413,69126', '8517,103690'], T1: ['25103,989788', '45453,1484681'], T0: ['1343,117003', '2133,175504']",
            "dgamma": "T0: ['1343,117003', '2133,175504'], T1: ['25103,989788', '45453,1484681'], T2: ['7413,69126', '8517,103690']",
            "connections": [
                0,
                1,
                2
            ],
            "overlapping_modes": {
                "0": "T0: 1343,117003, T1: 25103,989788, T2: 7413,69126, T2: 8517,103690",
                "1": "T0: 1343,117003, T1: 25103,989788, T1: 45453,1484681, T2: 7413,69126",
                "2": "T0: 1343,117003, T0: 2133,175504, T1: 25103,989788, T2: 7413,69126"
            }
        }
    ],
    "0.2": [
        {
            "U": 0.2,
            "ILP": true,
            "ILPDS": true,
            "gamma": "T2: ['1691,16160', '3205,24240'], T1: ['81,74863', '156,112295'], T0: ['12133,203999', '20319,305999']",
            "dgamma": "T0: ['12133,203999', '20319,305999'], T1: ['81,74863', '156,112295'], T2: ['1691,16160', '3205,24240']",
            "connections": [
                0,
                1,
                2,
                3
            ],
            "overlapping_modes": {
                "0": "T0: 12133,203999, T1: 81,74863, T2: 1691,16160, T2: 3205,24240",
                "1": "T0: 12133,203999, T1: 81,74863, T1: 156,112295, T2: 1691,16160",
                "2": "T0: 12133,203999, T1: 81,74863, T1: 156,112295, T2: 3205,24240",
                "3": "T0: 12133,203999, T0: 20319,305999, T1: 81,74863, T2: 3205,24240"
            }
        }
    ],
    "0.25": [
        {
            "U": 0.25,
            "ILP": true,
            "ILPDS": true,
            "gamma": "T2: ['82595,525855', '155599,788782'], T1: ['12896,305229', '15395,457844'], T0: ['5688,600150', '9440,900224']",
            "dgamma": "T0: ['5688,600150', '9440,900224'], T1: ['12896,305229', '15395,457844'], T2: ['82595,525855', '155599,788782']",
            "connections": [
                0,
                1,
                2
            ],
            "overlapping_modes": {
                "0": "T0: 5688,600150, T1: 12896,305229, T2: 82595,525855, T2: 155599,788782",
                "1": "T0: 5688,600150, T1: 12896,305229, T1: 15395,457844, T2: 82595,525855",
                "2": "T0: 5688,600150, T0: 9440,900224, T1: 12896,305229, T2: 82595,525855"
            }
        }
    ],
    "0.3": [
        {
            "U": 0.3,
            "ILP": true,
            "ILPDS": true,
            "gamma": "T2: ['17888,868355', '24604,1302533'], T1: ['2389,28834', '3658,43251'], T0: ['11846,60804', '16080,91206']",
            "dgamma": "T0: ['11846,60804', '16080,91206'], T1: ['2389,28834', '3658,43251'], T2: ['17888,868355', '24604,1302533']",
            "connections": [
                0,
                1,
                2
            ],
            "overlapping_modes": {
                "0": "T0: 11846,60804, T1: 2389,28834, T2: 17888,868355, T2: 24604,1302533",
                "1": "T0: 11846,60804, T1: 2389,28834, T1: 3658,43251, T2: 17888,868355",
                "2": "T0: 11846,60804, T0: 16080,91206, T1: 2389,28834, T2: 17888,868355"
            }
        }
    ],
    "0.35": [
        {
            "U": 0.35,
            "ILP": true,
            "ILPDS": true,
            "gamma": "T2: ['126598,601643', '220797,902465'], T1: ['2046,22665', '3529,33998'], T0: ['38,24413', '51,36619']",
            "dgamma": "T0: ['38,24413', '51,36619'], T1: ['2046,22665', '3529,33998'], T2: ['126598,601643', '220797,902465']",
            "connections": [
                0,
                1,
                2
            ],
            "overlapping_modes": {
                "0": "T0: 38,24413, T1: 2046,22665, T2: 126598,601643, T2: 220797,902465",
                "1": "T0: 38,24413, T1: 2046,22665, T1: 3529,33998, T2: 126598,601643",
                "2": "T0: 38,24413, T0: 51,36619, T1: 2046,22665, T2: 126598,601643"
            }
        }
    ],
    "0.4": [
        {
            "U": 0.4,
            "ILP": true,
            "ILPDS": true,
            "gamma": "T2: ['9024,549960', '11609,824941'], T1: ['6866,26868', '9420,40302'], T0: ['11738,96265', '18492,144398']",
            "dgamma": "T0: ['11738,96265', '18492,144398'], T1: ['6866,26868', '9420,40302'], T2: ['9024,549960', '11609,824941']",
            "connections": [
                0,
                1,
                2
            ],
            "overlapping_modes": {
                "0": "T0: 11738,96265, T1: 6866,26868, T2: 9024,549960, T2: 11609,824941",
                "1": "T0: 11738,96265, T1: 6866,26868, T1: 9420,40302, T2: 9024,549960",
                "2": "T0: 11738,96265, T0: 18492,144398, T1: 6866,26868, T2: 9024,549960"
            }
        }
    ],
    "0.45": [
        {
            "U": 0.45,
            "ILP": true,
            "ILPDS": true,
            "gamma": "T2: ['2331,23403', '4008,35105'], T1: ['6446,68401', '10844,102602'], T0: ['7559,40558', '14001,60837']",
            "dgamma": "T0: ['7559,40558', '14001,60837'], T1: ['6446,68401', '10844,102602'], T2: ['2331,23403', '4008,35105']",
            "connections": [
                0,
                1,
                2,
                3
            ],
            "overlapping_modes": {
                "0": "T0: 7559,40558, T1: 6446,68401, T2: 2331,23403, T2: 4008,35105",
                "1": "T0: 7559,40558, T1: 6446,68401, T1: 10844,102602, T2: 2331,23403",
                "2": "T0: 7559,40558, T1: 6446,68401, T1: 10844,102602, T2: 4008,35105",
                "3": "T0: 7559,40558, T0: 14001,60837, T1: 6446,68401, T2: 4008,35105"
            }
        }
    ],
    "0.5": [
        {
            "U": 0.5,
            "ILP": false,
            "ILPDS": false,
            "gamma": "T2: ['2424,10170', '2807,15255'], T1: ['90414,539667', '128027,809501'], T0: ['66405,741741', '104759,1112611']",
            "dgamma": null,
            "connections": null,
            "overlapping_modes": null
        }
    ],
    "0.55": [
        {
            "U": 0.55,
            "ILP": false,
            "ILPDS": false,
            "gamma": "T2: ['1003,11547', '1457,17320'], T1: ['119560,339281', '172225,508922'], T0: ['84092,771628', '128170,1157443']",
            "dgamma": null,
            "connections": null,
            "overlapping_modes": null
        }
    ],
    "0.6": [
        {
            "U": 0.6,
            "ILP": false,
            "ILPDS": false,
            "gamma": "T2: ['8282,51853', '14458,77780'], T1: ['161938,617646', '271822,926469'], T0: ['61051,505699', '85201,758549']",
            "dgamma": null,
            "connections": null,
            "overlapping_modes": null
        }
    ],
    "0.65": [
        {
            "U": 0.65,
            "ILP": true,
            "ILPDS": true,
            "gamma": "T2: ['5016,227436', '6548,341153'], T1: ['1393,95236', '2362,142855'], T0: ['59166,96769', '74957,145154']",
            "dgamma": "T0: ['59166,96769', '74957,145154'], T1: ['1393,95236', '2362,142855'], T2: ['5016,227436', '6548,341153']",
            "connections": [
                0,
                1,
                2,
                3,
                4
            ],
            "overlapping_modes": {
                "0": "T0: 59166,96769, T1: 1393,95236, T2: 5016,227436, T2: 6548,341153",
                "1": "T0: 59166,96769, T1: 1393,95236, T1: 2362,142855, T2: 5016,227436",
                "2": "T0: 59166,96769, T1: 1393,95236, T1: 2362,142855, T2: 6548,341153",
                "3": "T0: 59166,96769, T1: 2362,142855, T2: 5016,227436, T2: 6548,341153",
                "4": "T0: 59166,96769, T0: 74957,145154, T1: 2362,142855, T2: 5016,227436"
            }
        }
    ],
    "0.7": [
        {
            "U": 0.7,
            "ILP": false,
            "ILPDS": false,
            "gamma": "T2: ['78036,594332', '128413,891498'], T1: ['16096,90914', '25660,136371'], T0: ['70370,198361', '109434,297542']",
            "dgamma": null,
            "connections": null,
            "overlapping_modes": null
        }
    ],
    "0.75": [
        {
            "U": 0.75,
            "ILP": false,
            "ILPDS": false,
            "gamma": "T2: ['5598,52116', '7910,78174'], T1: ['8902,19292', '15020,28938'], T0: ['14576,139475', '25848,209212']",
            "dgamma": null,
            "connections": null,
            "overlapping_modes": null
        }
    ],
    "0.8": [
        {
            "U": 0.8,
            "ILP": false,
            "ILPDS": false,
            "gamma": "T2: ['23961,76739', '46118,115109'], T1: ['54238,251961', '86797,377941'], T0: ['19658,115842', '27393,173763']",
            "dgamma": null,
            "connections": null,
            "overlapping_modes": null
        }
    ],
    "0.85": [
        {
            "U": 0.85,
            "ILP": false,
            "ILPDS": false,
            "gamma": "T2: ['19462,206904', '29680,310356'], T1: ['119271,474140', '221865,711210'], T0: ['4520,10218', '5686,15327']",
            "dgamma": null,
            "connections": null,
            "overlapping_modes": null
        }
    ],
    "0.9": [
        {
            "U": 0.9,
            "ILP": true,
            "ILPDS": true,
            "gamma": "T2: ['30611,38844', '34822,58266'], T1: ['266,11459', '452,17188'], T0: ['8084,94349', '10123,141524']",
            "dgamma": "T0: ['8084,94349', '10123,141524'], T1: ['266,11459', '452,17188'], T2: ['30611,38844', '34822,58266']",
            "connections": [
                0,
                1,
                2
            ],
            "overlapping_modes": {
                "0": "T0: 8084,94349, T1: 266,11459, T2: 30611,38844, T2: 34822,58266",
                "1": "T0: 8084,94349, T1: 266,11459, T1: 452,17188, T2: 34822,58266",
                "2": "T0: 8084,94349, T0: 10123,141524, T1: 266,11459, T2: 34822,58266"
            }
        }
    ],
    "0.95": [
        {
            "U": 0.95,
            "ILP": true,
            "ILPDS": true,
            "gamma": "T2: ['59006,131067', '68256,196601'], T1: ['8717,94275', '16088,141412'], T0: ['12002,33142', '19191,49713']",
            "dgamma": "T0: ['12002,33142', '19191,49713'], T1: ['8717,94275', '16088,141412'], T2: ['59006,131067', '68256,196601']",
            "connections": [
                0,
                1,
                2
            ],
            "overlapping_modes": {
                "0": "T0: 12002,33142, T1: 8717,94275, T2: 59006,131067, T2: 68256,196601",
                "1": "T0: 12002,33142, T1: 8717,94275, T1: 16088,141412, T2: 68256,196601",
                "2": "T0: 12002,33142, T0: 19191,49713, T1: 8717,94275, T2: 68256,196601"
            }
        }
    ]
}