{
    "0.05": [
        {
            "U": 0.05,
            "ILP": true,
            "ILPDS": true,
            "gamma": "T2: ['9606,778906', '12960,1168360'], T1: ['4134,256574', '5869,384862'], T0: ['745,42090', '1361,63134']",
            "dgamma": "T0: ['745,42090', '1361,63134'], T1: ['4134,256574', '5869,384862'], T2: ['9606,778906', '12960,1168360']",
            "connections": [
                0,
                1,
                2
            ],
            "overlapping_modes": {
                "0": "T0: 745,42090, T1: 4134,256574, T2: 9606,778906, T2: 12960,1168360",
                "1": "T0: 745,42090, T1: 4134,256574, T1: 5869,384862, T2: 9606,778906",
                "2": "T0: 745,42090, T0: 1361,63134, T1: 4134,256574, T2: 9606,778906"
            }
        }
    ],
    "0.1": [
        {
            "U": 0.1,
            "ILP": true,
            "ILPDS": true,
            "gamma": "T2: ['2106,61873', '2504,92809'], T1: ['1597,98747', '2115,148120'], T0: ['446,10855', '811,16282']",
            "dgamma": "T0: ['446,10855', '811,16282'], T1: ['1597,98747', '2115,148120'], T2: ['2106,61873', '2504,92809']",
            "connections": [
                0,
                1,
                2
            ],
            "overlapping_modes": {
                "0": "T0: 446,10855, T1: 1597,98747, T2: 2106,61873, T2: 2504,92809",
                "1": "T0: 446,10855, T1: 1597,98747, T1: 2115,148120, T2: 2106,61873",
                "2": "T0: 446,10855, T0: 811,16282, T1: 1597,98747, T2: 2106,61873"
            }
        }
    ],
    "0.15": [
        {
            "U": 0.15,
            "ILP": true,
            "ILPDS": true,
            "gamma": "T2: ['43585,996518', '74616,1494777'], T1: ['1117,11276', '1570,16914'], T0: ['347,347868', '396,521802']",
            "dgamma": "T0: ['347,347868', '396,521802'], T1: ['1117,11276', '1570,16914'], T2: ['43585,996518', '74616,1494777']",
            "connections": [
                0,
                1,
                2
            ],
            "overlapping_modes": {
                "0": "T0: 347,347868, T1: 1117,11276, T2: 43585,996518, T2: 74616,1494777",
                "1": "T0: 347,347868, T1: 1117,11276, T1: 1570,16914, T2: 43585,996518",
                "2": "T0: 347,347868, T0: 396,521802, T1: 1117,11276, T2: 43585,996518"
            }
        }
    ],
    "0.2": [
        {
            "U": 0.2,
            "ILP": false,
            "ILPDS": false,
            "gamma": "T2: ['1309,38444', '1812,57666'], T1: ['2060,15602', '2700,23403'], T0: ['29655,875324', '44296,1312986']",
            "dgamma": null,
            "connections": null,
            "overlapping_modes": null
        }
    ],
    "0.25": [
        {
            "U": 0.25,
            "ILP": false,
            "ILPDS": false,
            "gamma": "T2: ['11973,318627', '15902,477941'], T1: ['3468,30198', '6154,45298'], T0: ['45856,623211', '71585,934816']",
            "dgamma": null,
            "connections": null,
            "overlapping_modes": null
        }
    ],
    "0.3": [
        {
            "U": 0.3,
            "ILP": true,
            "ILPDS": true,
            "gamma": "T2: ['2378,34329', '3514,51493'], T1: ['5170,28789', '6684,43184'], T0: ['5242,102467', '6790,153701']",
            "dgamma": "T0: ['5242,102467', '6790,153701'], T1: ['5170,28789', '6684,43184'], T2: ['2378,34329', '3514,51493']",
            "connections": [
                0,
                1,
                2
            ],
            "overlapping_modes": {
                "0": "T0: 5242,102467, T1: 5170,28789, T2: 2378,34329, T2: 3514,51493",
                "1": "T0: 5242,102467, T1: 5170,28789, T1: 6684,43184, T2: 2378,34329",
                "2": "T0: 5242,102467, T0: 6790,153701, T1: 5170,28789, T2: 2378,34329"
            }
        }
    ],
    "0.35": [
        {
            "U": 0.35,
            "ILP": true,
            "ILPDS": true,
            "gamma": "T2: ['2679,30961', '3988,46442'], T1: ['9537,252821', '13756,379231'], T0: ['7889,38840', '13152,58261']",
            "dgamma": "T0: ['7889,38840', '13152,58261'], T1: ['9537,252821', '13756,379231'], T2: ['2679,30961', '3988,46442']",
            "connections": [
                0,
                1,
                2
            ],
            "overlapping_modes": {
                "0": "T0: 7889,38840, T1: 9537,252821, T2: 2679,30961, T2: 3988,46442",
                "1": "T0: 7889,38840, T1: 9537,252821, T1: 13756,379231, T2: 2679,30961",
                "2": "T0: 7889,38840, T0: 13152,58261, T1: 9537,252821, T2: 2679,30961"
            }
        }
    ],
    "0.4": [
        {
            "U": 0.4,
            "ILP": true,
            "ILPDS": true,
            "gamma": "T2: ['13082,72469', '17521,108704'], T1: ['10931,105690', '21759,158535'], T0: ['12925,160599', '19808,240898']",
            "dgamma": "T0: ['12925,160599', '19808,240898'], T1: ['10931,105690', '21759,158535'], T2: ['13082,72469', '17521,108704']",
            "connections": [
                0,
                1,
                2
            ],
            "overlapping_modes": {
                "0": "T0: 12925,160599, T1: 10931,105690, T2: 13082,72469, T2: 17521,108704",
                "1": "T0: 12925,160599, T1: 10931,105690, T1: 21759,158535, T2: 13082,72469",
                "2": "T0: 12925,160599, T0: 19808,240898, T1: 10931,105690, T2: 13082,72469"
            }
        }
    ],
    "0.45": [
        {
            "U": 0.45,
            "ILP": false,
            "ILPDS": false,
            "gamma": "T2: ['1704,11831', '2566,17747'], T1: ['3296,33914', '6479,50871'], T0: ['24638,153608', '41031,230412']",
            "dgamma": null,
            "connections": null,
            "overlapping_modes": null
        }
    ],
    "0.5": [
        {
            "U": 0.5,
            "ILP": true,
            "ILPDS": true,
            "gamma": "T2: ['36072,220610', '48628,330915'], T1: ['61391,373586', '91322,560379'], T0: ['4202,24406', '5983,36609']",
            "dgamma": "T0: ['4202,24406', '5983,36609'], T1: ['61391,373586', '91322,560379'], T2: ['36072,220610', '48628,330915']",
            "connections": [
                0,
                1,
                2
            ],
            "overlapping_modes": {
                "0": "T0: 4202,24406, T1: 61391,373586, T2: 36072,220610, T2: 48628,330915",
                "1": "T0: 4202,24406, T1: 61391,373586, T1: 91322,560379, T2: 36072,220610",
                "2": "T0: 4202,24406, T0: 5983,36609, T1: 61391,373586, T2: 36072,220610"
            }
        }
    ],
    "0.55": [
        {
            "U": 0.55,
            "ILP": false,
            "ILPDS": false,
            "gamma": "T2: ['6658,22420', '10119,33630'], T1: ['18532,196817', '21792,295225'], T0: ['8982,57966', '10640,86950']",
            "dgamma": null,
            "connections": null,
            "overlapping_modes": null
        }
    ],
    "0.6": [
        {
            "U": 0.6,
            "ILP": true,
            "ILPDS": true,
            "gamma": "T2: ['70731,305084', '125922,457627'], T1: ['55920,329993', '102152,494989'], T0: ['11198,94527', '15549,141791']",
            "dgamma": "T0: ['11198,94527', '15549,141791'], T1: ['55920,329993', '102152,494989'], T2: ['70731,305084', '125922,457627']",
            "connections": [
                0,
                1,
                2
            ],
            "overlapping_modes": {
                "0": "T0: 11198,94527, T1: 55920,329993, T2: 70731,305084, T2: 125922,457627",
                "1": "T0: 11198,94527, T1: 55920,329993, T1: 102152,494989, T2: 70731,305084",
                "2": "T0: 11198,94527, T0: 15549,141791, T1: 55920,329993, T2: 70731,305084"
            }
        }
    ],
    "0.65": [
        {
            "U": 0.65,
            "ILP": true,
            "ILPDS": true,
            "gamma": "T2: ['88934,183661', '162469,275492'], T1: ['3933,96187', '6244,144280'], T0: ['2558,179751', '4579,269626']",
            "dgamma": "T0: ['2558,179751', '4579,269626'], T1: ['3933,96187', '6244,144280'], T2: ['88934,183661', '162469,275492']",
            "connections": [
                0,
                1,
                2
            ],
            "overlapping_modes": {
                "0": "T0: 2558,179751, T1: 3933,96187, T2: 88934,183661, T2: 162469,275492",
                "1": "T0: 2558,179751, T1: 3933,96187, T1: 6244,144280, T2: 88934,183661",
                "2": "T0: 2558,179751, T0: 4579,269626, T1: 3933,96187, T2: 88934,183661"
            }
        }
    ],
    "0.7": [
        {
            "U": 0.7,
            "ILP": false,
            "ILPDS": false,
            "gamma": "T2: ['1006,19857', '1645,29785'], T1: ['50679,338758', '67223,508137'], T0: ['30170,71737', '53282,107605']",
            "dgamma": null,
            "connections": null,
            "overlapping_modes": null
        }
    ],
    "0.75": [
        {
            "U": 0.75,
            "ILP": true,
            "ILPDS": true,
            "gamma": "T2: ['10139,51115', '12845,76673'], T1: ['15616,33692', '21049,50538'], T0: ['1566,17769', '2193,26653']",
            "dgamma": "T0: ['1566,17769', '2193,26653'], T1: ['15616,33692', '21049,50538'], T2: ['10139,51115', '12845,76673']",
            "connections": [
                0,
                1,
                2
            ],
            "overlapping_modes": {
                "0": "T0: 1566,17769, T1: 15616,33692, T2: 10139,51115, T2: 12845,76673",
                "1": "T0: 1566,17769, T0: 2193,26653, T1: 15616,33692, T2: 10139,51115",
                "2": "T0: 1566,17769, T1: 15616,33692, T1: 21049,50538, T2: 12845,76673"
            }
        }
    ],
    "0.8": [
        {
            "U": 0.8,
            "ILP": true,
            "ILPDS": true,
            "gamma": "T2: ['241195,782349', '373826,1173524'], T1: ['13249,70446', '21699,105669'], T0: ['7946,29896', '12381,44844']",
            "dgamma": "T0: ['7946,29896', '12381,44844'], T1: ['13249,70446', '21699,105669'], T2: ['241195,782349', '373826,1173524']",
            "connections": [
                0,
                1,
                2
            ],
            "overlapping_modes": {
                "0": "T0: 7946,29896, T1: 13249,70446, T2: 241195,782349, T2: 373826,1173524",
                "1": "T0: 7946,29896, T1: 13249,70446, T1: 21699,105669, T2: 241195,782349",
                "2": "T0: 7946,29896, T0: 12381,44844, T1: 13249,70446, T2: 241195,782349"
            }
        }
    ],
    "0.85": [
        {
            "U": 0.85,
            "ILP": false,
            "ILPDS": false,
            "gamma": "T2: ['6254,61050', '11249,91575'], T1: ['5160,37113', '8514,55670'], T0: ['139488,244606', '210686,366909']",
            "dgamma": null,
            "connections": null,
            "overlapping_modes": null
        }
    ],
    "0.9": [
        {
            "U": 0.9,
            "ILP": false,
            "ILPDS": true,
            "gamma": "T2: ['58694,347597', '70208,521395'], T1: ['69805,485249', '110131,727873'], T0: ['23629,42736', '37170,64103']",
            "dgamma": "T0: ['23629,42736', '37170,64103'], T1: ['69805,485249', '110131,727873'], T2: ['58694,347597', '70208,521395']",
            "connections": [
                0,
                1,
                2
            ],
            "overlapping_modes": {
                "0": "T0: 23629,42736, T1: 69805,485249, T2: 58694,347597, T2: 70208,521395",
                "1": "T0: 23629,42736, T1: 69805,485249, T1: 110131,727873, T2: 70208,521395",
                "2": "T0: 23629,42736, T0: 37170,64103, T1: 69805,485249, T2: 70208,521395"
            }
        }
    ],
    "0.95": [
        {
            "U": 0.95,
            "ILP": false,
            "ILPDS": false,
            "gamma": "T2: ['22253,77593', '38820,116389'], T1: ['68788,136357', '106515,204536'], T0: ['31079,324762', '42854,487143']",
            "dgamma": null,
            "connections": null,
            "overlapping_modes": null
        }
    ]
}