{
    "0.05": [
        {
            "U": 0.05,
            "ILP": true,
            "ILPDS": true,
            "gamma": "T2: ['10204,269068', '13720,403602'], T1: ['55,64469', '107,96703'], T0: ['160,14556', '212,21834']",
            "dgamma": "T0: ['160,14556', '212,21834'], T1: ['55,64469', '107,96703'], T2: ['10204,269068', '13720,403602']",
            "connections": [
                0,
                1,
                2
            ],
            "overlapping_modes": {
                "0": "T0: 160,14556, T1: 55,64469, T2: 10204,269068, T2: 13720,403602",
                "1": "T0: 160,14556, T1: 55,64469, T1: 107,96703, T2: 10204,269068",
                "2": "T0: 160,14556, T0: 212,21834, T1: 55,64469, T2: 10204,269068"
            }
        }
    ],
    "0.1": [
        {
            "U": 0.1,
            "ILP": false,
            "ILPDS": false,
            "gamma": "T2: ['12,11154', '18,16730'], T1: ['7389,108798', '12956,163198'], T0: ['3804,194904', '5464,292356']",
            "dgamma": null,
            "connections": null,
            "overlapping_modes": null
        }
    ],
    "0.15": [
        {
            "U": 0.15,
            "ILP": true,
            "ILPDS": true,
            "gamma": "T2: ['2697,80614', '4590,120921'], T1: ['15395,240572', '21898,360857'], T0: ['26072,542629', '36749,813943']",
            "dgamma": "T0: ['26072,542629', '36749,813943'], T1: ['15395,240572', '21898,360857'], T2: ['2697,80614', '4590,120921']",
            "connections": [
                0,
                1,
                2
            ],
            "overlapping_modes": {
                "0": "T0: 26072,542629, T1: 15395,240572, T2: 2697,80614, T2: 4590,120921",
                "1": "T0: 26072,542629, T1: 15395,240572, T1: 21898,360857, T2: 2697,80614",
                "2": "T0: 26072,542629, T0: 36749,813943, T1: 15395,240572, T2: 2697,80614"
            }
        }
    ],
    "0.2": [
        {
            "U": 0.2,
            "ILP": true,
            "ILPDS": true,
            "gamma": "T2: ['580,10999', '769,16499'], T1: ['3325,47503', '4246,71254'], T0: ['3178,41098', '3745,61648']",
            "dgamma": "T0: ['3178,41098', '3745,61648'], T1: ['3325,47503', '4246,71254'], T2: ['580,10999', '769,16499']",
            "connections": [
                0,
                1,
                2
            ],
            "overlapping_modes": {
                "0": "T0: 3178,41098, T1: 3325,47503, T2: 580,10999, T2: 769,16499",
                "1": "T0: 3178,41098, T1: 3325,47503, T1: 4246,71254, T2: 580,10999",
                "2": "T0: 3178,41098, T0: 3745,61648, T1: 3325,47503, T2: 580,10999"
            }
        }
    ],
    "0.25": [
        {
            "U": 0.25,
            "ILP": false,
            "ILPDS": false,
            "gamma": "T2: ['513,17505', '674,26257'], T1: ['939,16058', '1860,24087'], T0: ['33754,252115', '54258,378172']",
            "dgamma": null,
            "connections": null,
            "overlapping_modes": null
        }
    ],
    "0.3": [
        {
            "U": 0.3,
            "ILP": true,
            "ILPDS": true,
            "gamma": "T2: ['14894,202438', '29386,303658'], T1: ['139647,865816', '255485,1298725'], T0: ['830,127499', '1028,191248']",
            "dgamma": "T0: ['830,127499', '1028,191248'], T1: ['139647,865816', '255485,1298725'], T2: ['14894,202438', '29386,303658']",
            "connections": [
                0,
                1,
                2
            ],
            "overlapping_modes": {
                "0": "T0: 830,127499, T1: 139647,865816, T2: 14894,202438, T2: 29386,303658",
                "1": "T0: 830,127499, T0: 1028,191248, T1: 139647,865816, T2: 14894,202438",
                "2": "T0: 830,127499, T1: 139647,865816, T1: 255485,1298725, T2: 29386,303658"
            }
        }
    ],
    "0.35": [
        {
            "U": 0.35,
            "ILP": true,
            "ILPDS": true,
            "gamma": "T2: ['47677,185683', '54575,278524'], T1: ['10063,211781', '16175,317672'], T0: ['493,12954', '822,19431']",
            "dgamma": "T0: ['493,12954', '822,19431'], T1: ['10063,211781', '16175,317672'], T2: ['47677,185683', '54575,278524']",
            "connections": [
                0,
                1,
                2
            ],
            "overlapping_modes": {
                "0": "T0: 493,12954, T1: 10063,211781, T2: 47677,185683, T2: 54575,278524",
                "1": "T0: 493,12954, T1: 10063,211781, T1: 16175,317672, T2: 47677,185683",
                "2": "T0: 493,12954, T0: 822,19431, T1: 10063,211781, T2: 47677,185683"
            }
        }
    ],
    "0.4": [
        {
            "U": 0.4,
            "ILP": false,
            "ILPDS": false,
            "gamma": "T2: ['3815,18545', '4520,27817'], T1: ['2549,287194', '2912,430791'], T0: ['142084,766253', '165135,1149379']",
            "dgamma": null,
            "connections": null,
            "overlapping_modes": null
        }
    ],
    "0.45": [
        {
            "U": 0.45,
            "ILP": false,
            "ILPDS": false,
            "gamma": "T2: ['1319,70981', '2088,106471'], T1: ['107177,404877', '187046,607315'], T0: ['8885,72592', '12635,108888']",
            "dgamma": null,
            "connections": null,
            "overlapping_modes": null
        }
    ],
    "0.5": [
        {
            "U": 0.5,
            "ILP": true,
            "ILPDS": true,
            "gamma": "T2: ['38851,95762', '57111,143643'], T1: ['14060,248999', '21473,373499'], T0: ['22709,617035', '28602,925553']",
            "dgamma": "T0: ['22709,617035', '28602,925553'], T1: ['14060,248999', '21473,373499'], T2: ['38851,95762', '57111,143643']",
            "connections": [
                0,
                1,
                2
            ],
            "overlapping_modes": {
                "0": "T0: 22709,617035, T1: 14060,248999, T2: 38851,95762, T2: 57111,143643",
                "1": "T0: 22709,617035, T1: 14060,248999, T1: 21473,373499, T2: 38851,95762",
                "2": "T0: 22709,617035, T0: 28602,925553, T1: 14060,248999, T2: 38851,95762"
            }
        }
    ],
    "0.55": [
        {
            "U": 0.55,
            "ILP": false,
            "ILPDS": false,
            "gamma": "T2: ['124380,430141', '201597,645211'], T1: ['5,14244', '9,21366'], T0: ['205545,866785', '304328,1300177']",
            "dgamma": null,
            "connections": null,
            "overlapping_modes": null
        }
    ],
    "0.6": [
        {
            "U": 0.6,
            "ILP": false,
            "ILPDS": false,
            "gamma": "T2: ['2895,11752', '3920,17628'], T1: ['1237,11771', '1583,17656'], T0: ['15317,67632', '25213,101448']",
            "dgamma": null,
            "connections": null,
            "overlapping_modes": null
        }
    ],
    "0.65": [
        {
            "U": 0.65,
            "ILP": true,
            "ILPDS": true,
            "gamma": "T2: ['24184,70450', '32698,105675'], T1: ['22454,88065', '39912,132098'], T0: ['219,63451', '436,95176']",
            "dgamma": "T0: ['219,63451', '436,95176'], T1: ['22454,88065', '39912,132098'], T2: ['24184,70450', '32698,105675']",
            "connections": [
                0,
                1,
                2
            ],
            "overlapping_modes": {
                "0": "T0: 219,63451, T1: 22454,88065, T2: 24184,70450, T2: 32698,105675",
                "1": "T0: 219,63451, T1: 22454,88065, T1: 39912,132098, T2: 24184,70450",
                "2": "T0: 219,63451, T0: 436,95176, T1: 22454,88065, T2: 24184,70450"
            }
        }
    ],
    "0.7": [
        {
            "U": 0.7,
            "ILP": true,
            "ILPDS": true,
            "gamma": "T2: ['1766,11528', '2329,17291'], T1: ['705,14130', '854,21195'], T0: ['5009,10082', '6137,15123']",
            "dgamma": "T0: ['5009,10082', '6137,15123'], T1: ['705,14130', '854,21195'], T2: ['1766,11528', '2329,17291']",
            "connections": [
                0,
                1,
                2,
                3
            ],
            "overlapping_modes": {
                "0": "T0: 5009,10082, T1: 705,14130, T2: 1766,11528, T2: 2329,17291",
                "1": "T0: 5009,10082, T1: 705,14130, T1: 854,21195, T2: 1766,11528",
                "2": "T0: 5009,10082, T1: 705,14130, T1: 854,21195, T2: 2329,17291",
                "3": "T0: 5009,10082, T0: 6137,15123, T1: 705,14130, T2: 2329,17291"
            }
        }
    ],
    "0.75": [
        {
            "U": 0.75,
            "ILP": true,
            "ILPDS": true,
            "gamma": "T2: ['218862,298772', '323740,448158'], T1: ['9367,647509', '16899,971263'], T0: ['11,191484', '18,287226']",
            "dgamma": "T0: ['11,191484', '18,287226'], T1: ['9367,647509', '16899,971263'], T2: ['218862,298772', '323740,448158']",
            "connections": [
                0,
                1,
                2
            ],
            "overlapping_modes": {
                "0": "T0: 11,191484, T1: 9367,647509, T2: 218862,298772, T2: 323740,448158",
                "1": "T0: 11,191484, T1: 9367,647509, T1: 16899,971263, T2: 218862,298772",
                "2": "T0: 11,191484, T0: 18,287226, T1: 9367,647509, T2: 218862,298772"
            }
        }
    ],
    "0.8": [
        {
            "U": 0.8,
            "ILP": false,
            "ILPDS": false,
            "gamma": "T2: ['5235,55764', '6509,83646'], T1: ['25299,48053', '44270,72080'], T0: ['25930,282032', '38384,423048']",
            "dgamma": null,
            "connections": null,
            "overlapping_modes": null
        }
    ],
    "0.85": [
        {
            "U": 0.85,
            "ILP": false,
            "ILPDS": false,
            "gamma": "T2: ['6400,484590', '10715,726884'], T1: ['60534,243130', '108235,364695'], T0: ['395043,810507', '654659,1215760']",
            "dgamma": null,
            "connections": null,
            "overlapping_modes": null
        }
    ],
    "0.9": [
        {
            "U": 0.9,
            "ILP": false,
            "ILPDS": false,
            "gamma": "T2: ['52857,255958', '90648,383937'], T1: ['16774,61205', '26347,91808'], T0: ['35649,98484', '55681,147727']",
            "dgamma": null,
            "connections": null,
            "overlapping_modes": null
        }
    ],
    "0.95": [
        {
            "U": 0.95,
            "ILP": false,
            "ILPDS": false,
            "gamma": "T2: ['100811,433488', '126791,650231'], T1: ['16409,55668', '28624,83501'], T0: ['242623,647608', '326481,971412']",
            "dgamma": null,
            "connections": null,
            "overlapping_modes": null
        }
    ]
}